envassume/__init__.py
envassume/arguments.py
envassume/exceptions.py
envassume/main.py
envassume/usage.py
envassume-1.0.7.dist-info/LICENSE
envassume-1.0.7.dist-info/METADATA
envassume-1.0.7.dist-info/WHEEL
envassume-1.0.7.dist-info/entry_points.txt
envassume-1.0.7.dist-info/top_level.txt
envassume-1.0.7.dist-info/RECORD
