Metadata-Version: 2.1
Name: envassume
Version: 1.0.7
Summary: Assume an AWS IAM role and execute a command with the assumed credentials
Home-page: https://github.com/wamonite/envassume
Author: Warren Moore
Author-email: warren@wamonite.com
License: MIT
Platform: UNKNOWN
Classifier: Development Status :: 5 - Production/Stable
Classifier: Intended Audience :: Developers
Classifier: Intended Audience :: System Administrators
Classifier: Environment :: Console
Classifier: License :: OSI Approved :: MIT License
Classifier: Natural Language :: English
Classifier: Operating System :: OS Independent
Classifier: Programming Language :: Python :: 2
Classifier: Programming Language :: Python :: 3
Classifier: Topic :: Utilities
Requires-Dist: boto3
Requires-Dist: attrs
